{
  "$6000": "unknown",
  "$601a": "timer_constantly_counts_down",
  "$603a": "unknown",
  "$6080": "walking_sound_buffer",
  "$6081": "sound_buffer_address_for_jumping",
  "$6082": "boom_sound_address",
  "$6083": "play_sound_for_bouncer",
  "$6084": "play_sound_for_falling_bouncer",
  "$6085": "play_sound_for_bonus",
  "$6088": "play_death_sound",
  "$6089": "background_music_value",
  "$608a": "sound_buffer_address",
  "$608b": "music_timer",
  "$60b0": "task_list_pointer",
  "$60b1": "the_task_pointer",
  "$60b2": "player_1_score_address",
  "$60b3": "address_for_player_1_score",
  "$60b4": "player_1_score",
  "$60b5": "player_2_score_address",
  "$60b6": "address_of_player_2_score",
  "$60b7": "player_2_score",
  "$60b8": "high_score",
  "$60ba": "high_score",
  "$60c0": "start_of_task_list",
  "$6100": "high_score_ram",
  "$611c": "address_of_high_score_indicator",
  "$61a5": "lowest_high_score_address",
  "$61b1": "unknown",
  "$61c6": "address_for_unknown",
  "$61c7": "copy_of_player_score",
  "$6200": "mario_array",
  "$6202": "put_back",
  "$6203": "jump_if_bit_7_of_mario_x_position_is_set",
  "$6204": "unknown",
  "$6205": "return_without_taking_the_ladder",
  "$6206": "unknown",
  "$6207": "mario_movement_indicator_sprite_value",
  "$6208": "mario_color",
  "$6209": "unknown",
  "$620c": "mario_jump_height",
  "$620e": "unknown",
  "$620f": "address_of_movement_indicator",
  "$6210": "mario_jump_direction",
  "$6211": "unknown",
  "$6212": "this_indicator",
  "$6213": "unknown",
  "$6214": "jump_counter",
  "$6215": "ladder_status",
  "$6216": "jumping_status",
  "$6217": "unknown",
  "$6218": "mario_is_grabbing_the_hammer_until_he_lands",
  "$6219": "store_1_into_status_indicator",
  "$621a": "moving_ladder_indicator",
  "$621c": "y_value_of_top_of_ladder",
  "$621e": "jump_coming_down_indicator",
  "$621f": "mario_jump_apex",
  "$6220": "falling_too_far_indicator",
  "$6221": "mario_falling_indicator",
  "$6222": "ladder_toggle",
  "$6224": "store_result",
  "$6225": "bonus_sound_indicator",
  "$6227": "screen_number",
  "$6228": "number_of_lives_remaining",
  "$6229": "else_level_number",
  "$622a": "store",
  "$622c": "game_start_flag",
  "$622d": "extra_life_indicator",
  "$622e": "number_of_goofys_to_draw",
  "$622f": "current_screen_level",
  "$6280": "left_side_rectractable_ladder",
  "$6288": "right_side_retractable_ladder",
  "$6290": "number_of_rivets_left",
  "$6291": "column_indicator",
  "$6292": "start_of_array_of_rivets",
  "$62a0": "top_conveyor_counter",
  "$62a1": "master_direction_vector_for_top_conveyor",
  "$62a3": "master_direction_vector_for_upper_left",
  "$62a5": "this_counter",
  "$62a6": "master_direction_vector_for_lower_level",
  "$62a7": "elevator_counter_address",
  "$62a8": "unknown",
  "$62aa": "barrel_start_address",
  "$62ac": "sprite_variable_start",
  "$62af": "kong_climbing_counter",
  "$62b0": "initial_clock_value",
  "$62b1": "bonus_timer",
  "$62b2": "blue_barrel_counter",
  "$62b3": "intial_timer_value",
  "$62b4": "timer",
  "$62b8": "this_counter",
  "$62b9": "fire_release",
  "$62ba": "timer_reset",
  "$6300": "ladder_positions",
  "$6310": "unknown",
  "$6340": "bonus_indicator",
  "$6341": "timer",
  "$6342": "scoring_indicator",
  "$6343": "unknown_for_use_later",
  "$6345": "item_hit_phase_counter_address",
  "$6346": "timer",
  "$6348": "the_oil_can_is_on_fire",
  "$6350": "item_hit_indicator_unknown",
  "$6351": "unknown",
  "$6352": "unknown",
  "$6353": "unknown",
  "$6354": "unknown",
  "$6380": "unknown",
  "$6381": "timer",
  "$6382": "crazy_blue_barrel_indicator",
  "$6383": "memory_used_to_track_tasks",
  "$6384": "timer_address",
  "$6385": "intro_screen_counter",
  "$6386": "time_has_run_out_indicator",
  "$6387": "timer_address",
  "$6388": "end_of_level_counter",
  "$6389": "restored_when_hammer_runs_out",
  "$638a": "kong_intro_flash_counter",
  "$638b": "unknown",
  "$638c": "reset_onscreen_timer",
  "$638d": "kong_bounce_counter",
  "$638e": "kong_ladder_climb_counter",
  "$638f": "deployment_indicator",
  "$6390": "timer_unknown",
  "$6391": "indicator",
  "$6392": "barrel_deployment_indicator",
  "$6393": "barrel_deployment_indicator",
  "$6394": "hammer_timer",
  "$6395": "hammer_length",
  "$6396": "bouncer_release",
  "$6398": "elevator_status",
  "$639a": "deployment_indicator",
  "$639b": "pie_timer_for_next_pie_deployment",
  "$639d": "death_indicator",
  "$639e": "load_counter",
  "$63a0": "unknown",
  "$63a1": "unknown",
  "$63a2": "unknown",
  "$63a3": "top_conveyor_direction_vector",
  "$63a4": "upper_left_pie_tray_vector",
  "$63a5": "upper_right_pie_tray_vector",
  "$63a6": "pie_direction_lower_level",
  "$63a7": "store",
  "$63a8": "result",
  "$63ab": "unknown",
  "$63ad": "unknown",
  "$63af": "original_data_item_",
  "$63b0": "unknown",
  "$63b1": "result",
  "$63b2": "unknown",
  "$63b3": "original_data_item",
  "$63b4": "unknown",
  "$63b5": "unknown",
  "$63b7": "kongs_position",
  "$63b8": "mario_dead_flag",
  "$63b9": "counter_for_use_later",
  "$63c0": "timer_unknown",
  "$63c2": "store",
  "$63c4": "unknown",
  "$63c8": "address_of_fireball_slot_for_this_fireball",
  "$63cc": "state_of_attract_mode",
  "$63e0": "current_fireball_data_address",
  "$6400": "start_of_fires_table",
  "$6407": "unknown",
  "$6439": "freezer_indicator_of_2nd_fire",
  "$6479": "freezer_indicator_of_4th_fire",
  "$64a0": "address_of_black_square_sprite_start",
  "$64a3": "destination_?",
  "$64a7": "set_destination_sprites",
  "$6500": "start_of_bouncer_memory_area",
  "$6507": "destination",
  "$65a0": "start_of_pies",
  "$65a7": "destination_is_#65a7",
  "$6600": "elevator_array_start",
  "$6603": "destination_sprite_?_x_positions_?",
  "$6607": "destination_sprite_?",
  "$660d": "unknown",
  "$6680": "software_address_of_hammer_sprite",
  "$6683": "sprite_destination_address_unknown",
  "$6687": "unknown",
  "$6690": "second_hammer_sprite",
  "$66a0": "oil_can_address",
  "$6700": "start_of_barrel_info_table",
  "$6707": "destination",
  "$6807": "destination",
  "$6900": "girls_head_sprite",
  "$6901": "unknown",
  "$6903": "sprite_girl_table_data_y_position",
  "$6904": "girls_body_sprite",
  "$6905": "girls_sprite",
  "$6908": "start_of_kong_sprite",
  "$6909": "kongs_right_leg_address_sprite",
  "$690b": "kong_sprite_array",
  "$690c": "clear_kongs_top_right_sprite",
  "$6910": "kongs_x_position",
  "$6913": "kong_sprite_y_position",
  "$6919": "unknown",
  "$691b": "unknown",
  "$691d": "kongs_right_arm_address_sprite",
  "$6924": "kongs_right_arm_sprite_for_carrying_girl",
  "$692c": "girl_being_carried_sprite",
  "$692d": "sprite_of_girl_under_kongs_arms",
  "$692f": "girl_under_kongs_arm_y_position",
  "$6944": "sprite_start_for_moving_ladders",
  "$6947": "other_ladder_sprite_y_value",
  "$694b": "ladder_sprite_y_value",
  "$694c": "mario_sprite_x_position",
  "$694d": "mario_sprite_value",
  "$694f": "mario_sprite_y_value",
  "$6950": "start_of_hammers",
  "$6958": "elevator_sprites",
  "$6970": "sprites_used_at_top_and_bottom_of_elevators",
  "$6974": "unknown",
  "$6980": "start_of_sprite_memory_for_bouncers",
  "$69a8": "extra_barrels_sprites",
  "$69b8": "start_of_pie_sprites",
  "$69d0": "start_of_firefox_sprites",
  "$69e4": "start_of_pulley_sprites",
  "$69ec": "middle_pulley_sprites",
  "$69ed": "unknown",
  "$69f4": "pulley_sprite_start",
  "$69fc": "unknown_sprite",
  "$6a00": "blank_space_sprite",
  "$6a0c": "start_of_bonus_items",
  "$6a18": "hardware_address_of_hammer_sprite",
  "$6a1c": "hardware_address_of_2nd_hammer_sprite",
  "$6a20": "heart_sprite_x_position",
  "$6a21": "heart_sprite",
  "$6a23": "heart_sprite",
  "$6a24": "sprite_address_used_for_kong_aching_head_lines",
  "$6a25": "unknown",
  "$6a28": "hardware_sprite_memory_for_same_fire",
  "$6a29": "sprite_for_fire_above_oil_can",
  "$6a2c": "location_of_item_hit",
  "$6a2d": "sprite_graphic",
  "$6a30": "unknown",
  "$6c00": "stack_pointer"
}